SPI.v
module SPI(input cs,input sclk,input mosi,output reg miso=0);
    parameter S0 = 4'd0;
    parameter S1 = 4'd1;
    parameter S2 = 4'd2;
    parameter S3 = 4'd3;
    parameter S4 = 4'd4;
    parameter S5 = 4'd5;
    parameter S6 = 4'd6;
    parameter S7 = 4'd7;
    reg [7:0] buffer_s = 8'd0;
    reg s7 = 0;
    always @(posedge sclk) 
    begin
        if(!cs)
        begin
            s7 <= buffer_s[7];
            buffer_s <= buffer_s << 1'b1;
            buffer_s[0] <= mosi;
            miso <= s7;
            
        end
    
    end
endmodule

moudule_tb.v
// Define la escala de tiempo de la simulación: <time_unit> / <time_precision>
`timescale 10 ns / 100 ps
`include  "SPI.v"
// Nombre del testbench
module moudule_tb();

		//señales que se capturan del modulo bajo pruebas (DUT)
    wire    miso;

    // Señales con las que se estimula el modulo bajo pruebas
    reg     clk = 0;
    reg     rst = 0;      
    reg     cs = 1;
    reg     mosi = 0;
    reg     [7:0] buffer_m = 8'b11111111;
    reg      m7 = 0;
    reg     f = 0;      

    // Tiempo de simulación: 10000 * 10 ns = 100 us
    localparam DURATION = 100;
    
    // Simulación del clock: 1 / ((2 * 1) * 10 ns) = 50 MHz
    always begin
        
        // Delay de 1 <time units>
        #1
        
        // Toggle clock
        clk = ~clk;
    end

		// Gener una pulso breve para initializar internamente el modulo de pruebas
    initial begin
        #10
        rst = 1'b1;
        #1
        rst = 1'b0;
    end
    
    SPI slv(cs, clk, mosi, miso);

    // Controla lo relacionado a la simulación
    initial begin

        $dumpfile("tb.vcd");
        $dumpvars(0, moudule_tb);
        
        // Espera a que el tiempo de simulación se cumpla
        #(DURATION)
        
        // Mesaje indicando que la simulación ha terminado
        $display("Finished!");
        $finish;
    end

	initial begin
		
		//para analizar las salidas o generar otros estimulos.
    //Inicio de definición del modulo maestro
    
    #15
    cs = 1;
    m7 <= buffer_m[7];
    buffer_m <= buffer_m << 1'b1;
    buffer_m[0] <= miso;
    mosi <= m7;
    #1
    cs=0;
    #1
    cs = 1;
    m7 <= buffer_m[7];
    buffer_m <= buffer_m << 1'b1;
    buffer_m[0] <= miso;
    mosi <= m7;
    #1
    cs=0;
    #1
    cs = 1;
    m7 <= buffer_m[7];
    buffer_m <= buffer_m << 1'b1;
    buffer_m[0] <= miso;
    mosi <= m7;
    #1
    cs=0;
    
    
    
   

	end


endmodule

build/tb.vcd
$date
	Thu Mar 14 13:29:26 2024
$end
$version
	Icarus Verilog
$end
$timescale
	100ps
$end
$scope module moudule_tb $end
$var wire 1 ! miso $end
$var parameter 32 " DURATION $end
$var reg 8 # buffer_m [7:0] $end
$var reg 1 $ clk $end
$var reg 1 % cs $end
$var reg 1 & f $end
$var reg 1 ' m7 $end
$var reg 1 ( mosi $end
$var reg 1 ) rst $end
$scope module slv $end
$var wire 1 % cs $end
$var wire 1 ( mosi $end
$var wire 1 $ sclk $end
$var parameter 4 * S0 $end
$var parameter 4 + S1 $end
$var parameter 4 , S2 $end
$var parameter 4 - S3 $end
$var parameter 4 . S4 $end
$var parameter 4 / S5 $end
$var parameter 4 0 S6 $end
$var parameter 4 1 S7 $end
$var reg 8 2 buffer_s [7:0] $end
$var reg 1 ! miso $end
$var reg 1 3 s7 $end
$upscope $end
$upscope $end
$enddefinitions $end
$comment Show the parameter values. $end
$dumpall
b111 1
b110 0
b101 /
b100 .
b11 -
b10 ,
b1 +
b0 *
b1100100 "
$end
#0
$dumpvars
03
b0 2
0)
0(
0'
0&
1%
0$
b11111111 #
0!
$end
#100
1$
#200
0$
#300
1$
#400
0$
#500
1$
#600
0$
#700
1$
#800
0$
#900
1$
#1000
0$
1)
#1100
1$
0)
#1200
0$
#1300
1$
#1400
0$
#1500
b11111110 #
1'
1$
#1600
0$
0%
#1700
1(
b11111100 #
1$
1%
#1800
0$
0%
#1900
b11111000 #
1$
1%
#2000
0$
0%
#2100
b1 2
1$
#2200
0$
#2300
b11 2
1$
#2400
0$
#2500
b111 2
1$
#2600
0$
#2700
b1111 2
1$
#2800
0$
#2900
b11111 2
1$
#3000
0$
#3100
b111111 2
1$
#3200
0$
#3300
b1111111 2
1$
#3400
0$
#3500
b11111111 2
1$
#3600
0$
#3700
b11111111 2
13
1$
#3800
0$
#3900
1!
b11111111 2
1$
#4000
0$
#4100
b11111111 2
1$
#4200
0$
#4300
b11111111 2
1$
#4400
0$
#4500
b11111111 2
1$
#4600
0$
#4700
b11111111 2
1$
#4800
0$
#4900
b11111111 2
1$
#5000
0$
#5100
b11111111 2
1$
#5200
0$
#5300
b11111111 2
1$
#5400
0$
#5500
b11111111 2
1$
#5600
0$
#5700
b11111111 2
1$
#5800
0$
#5900
b11111111 2
1$
#6000
0$
#6100
b11111111 2
1$
#6200
0$
#6300
b11111111 2
1$
#6400
0$
#6500
b11111111 2
1$
#6600
0$
#6700
b11111111 2
1$
#6800
0$
#6900
b11111111 2
1$
#7000
0$
#7100
b11111111 2
1$
#7200
0$
#7300
b11111111 2
1$
#7400
0$
#7500
b11111111 2
1$
#7600
0$
#7700
b11111111 2
1$
#7800
0$
#7900
b11111111 2
1$
#8000
0$
#8100
b11111111 2
1$
#8200
0$
#8300
b11111111 2
1$
#8400
0$
#8500
b11111111 2
1$
#8600
0$
#8700
b11111111 2
1$
#8800
0$
#8900
b11111111 2
1$
#9000
0$
#9100
b11111111 2
1$
#9200
0$
#9300
b11111111 2
1$
#9400
0$
#9500
b11111111 2
1$
#9600
0$
#9700
b11111111 2
1$
#9800
0$
#9900
b11111111 2
1$
